README.md
setup.py
airscooter/__init__.py
airscooter/cli.py
airscooter/depositor.py
airscooter/orchestration.py
airscooter/transform.py
airscooter.egg-info/PKG-INFO
airscooter.egg-info/SOURCES.txt
airscooter.egg-info/dependency_links.txt
airscooter.egg-info/entry_points.txt
airscooter.egg-info/requires.txt
airscooter.egg-info/top_level.txt