Metadata-Version: 1.1
Name: airscooter
Version: 0.0.1
Summary: Simple data processing task graph manager for Python.
Home-page: https://github.com/ResidentMario/airscooter
Author: Aleksey Bilogur
Author-email: aleksey.bilogur@gmail.com
License: UNKNOWN
Download-URL: https://github.com/ResidentMario/airscooter/tarball/0.0.1
Keywords: data,data analysis,data science,task graph
Platform: UNKNOWN
